Metadata-Version: 1.0
Name: pak-unior
Version: 1.2.3
Summary: PAK UNIOR web plot
Home-page: https://github.com/ArtyomZemlyak/pak_unior
Author: ArtemZemliak
Author-email: artyom.zemlyak@gmail.com
License: OSL
Platform: UNKNOWN
